thunder_subtitle/__init__.py
thunder_subtitle/search.py
thunder_subtitle/thunder_subs.py
thunder_subtitle-0.1.2.dist-info/DESCRIPTION.rst
thunder_subtitle-0.1.2.dist-info/METADATA
thunder_subtitle-0.1.2.dist-info/RECORD
thunder_subtitle-0.1.2.dist-info/WHEEL
thunder_subtitle-0.1.2.dist-info/entry_points.txt
thunder_subtitle-0.1.2.dist-info/metadata.json
thunder_subtitle-0.1.2.dist-info/top_level.txt
