Metadata-Version: 2.0
Name: thunder-subtitle
Version: 0.1.2
Summary: 下载迅雷看看字幕
Home-page: https://github.com/weaming/thunder-subtitle
Author: weaming
Author-email: garden.yuen@gmail.com
License: UNKNOWN
Project-URL: Source, https://github.com/weaming/thunder-subtitle
Project-URL: Bug Reports, https://github.com/weaming/thunder-subtitle
Platform: UNKNOWN
Requires-Dist: drawtable
